whisper_blog_infimum-0.0.3-py3.9-nspkg.pth
whisper/infimum/__init__.py
whisper/infimum/config.py
whisper/infimum/py.typed
whisper/infimum/static/admin.js
whisper/infimum/static/common.css
whisper/infimum/static/list.css
whisper/infimum/static/post.css
whisper/infimum/template/404.html
whisper/infimum/template/base.html
whisper/infimum/template/list.html
whisper/infimum/template/post.html
whisper_blog_infimum-0.0.3.dist-info/LICENSE
whisper_blog_infimum-0.0.3.dist-info/METADATA
whisper_blog_infimum-0.0.3.dist-info/WHEEL
whisper_blog_infimum-0.0.3.dist-info/namespace_packages.txt
whisper_blog_infimum-0.0.3.dist-info/top_level.txt
whisper_blog_infimum-0.0.3.dist-info/RECORD
