Metadata-Version: 2.1
Name: whisper-blog-infimum
Version: 0.0.3
Summary: A minimalist theme for Whisper, a lightweight modularized blog engine
Home-page: https://ciel.dev/whisper/
Author: TechCiel
Author-email: whisper@ciel.dev
License: AGPL-3.0
Project-URL: Source Code, https://github.com/TechCiel/whisper/tree/infimum
Project-URL: Issue Tracker, https://github.com/TechCiel/whisper/issues
Classifier: Development Status :: 2 - Pre-Alpha
Classifier: Environment :: Web Environment
Classifier: Framework :: Flask
Classifier: Intended Audience :: Developers
Classifier: License :: OSI Approved :: GNU Affero General Public License v3
Classifier: Natural Language :: English
Classifier: Operating System :: OS Independent
Classifier: Programming Language :: Python :: 3.9
Classifier: Topic :: Internet :: WWW/HTTP :: Dynamic Content
Classifier: Topic :: Internet :: WWW/HTTP :: WSGI :: Application
Classifier: Typing :: Typed
Requires-Python: >=3.9
License-File: LICENSE
Requires-Dist: whisper-blog-core
Requires-Dist: whisper-blog-file
Requires-Dist: whisper-blog-markdown
